misata/__init__.py
misata/api.py
misata/audit.py
misata/benchmark.py
misata/cache.py
misata/cli.py
misata/codegen.py
misata/constraints.py
misata/context.py
misata/curve_fitting.py
misata/customization.py
misata/exceptions.py
misata/feedback.py
misata/formulas.py
misata/generators.py
misata/hybrid.py
misata/llm_parser.py
misata/noise.py
misata/profiles.py
misata/quality.py
misata/schema.py
misata/semantic.py
misata/simulator.py
misata/smart_values.py
misata/story_parser.py
misata/streaming.py
misata/validation.py
misata/generators/__init__.py
misata/generators/base.py
misata/templates/__init__.py
misata/templates/library.py
misata-0.3.0b0.dist-info/licenses/LICENSE
misata-0.3.0b0.dist-info/METADATA
misata-0.3.0b0.dist-info/WHEEL
misata-0.3.0b0.dist-info/entry_points.txt
misata-0.3.0b0.dist-info/top_level.txt
misata-0.3.0b0.dist-info/RECORD
