Metadata-Version: 2.4
Name: misata
Version: 0.3.0b0
Summary: AI-Powered Synthetic Data Engine - Generate realistic multi-table datasets from natural language
Author-email: Muhammed Rasin <rasinbinabdulla@gmail.com>
License: MIT
Project-URL: Homepage, https://github.com/rasinmuhammed/misata
Project-URL: Documentation, https://github.com/rasinmuhammed/misata#readme
Project-URL: Repository, https://github.com/rasinmuhammed/misata
Project-URL: Issues, https://github.com/rasinmuhammed/misata/issues
Keywords: synthetic-data,data-generation,fake-data,machine-learning,testing,llm,ai,database
Classifier: Development Status :: 4 - Beta
Classifier: Intended Audience :: Developers
Classifier: Intended Audience :: Science/Research
Classifier: License :: OSI Approved :: MIT License
Classifier: Operating System :: OS Independent
Classifier: Programming Language :: Python :: 3
Classifier: Programming Language :: Python :: 3.10
Classifier: Programming Language :: Python :: 3.11
Classifier: Programming Language :: Python :: 3.12
Classifier: Topic :: Software Development :: Testing
Classifier: Topic :: Scientific/Engineering :: Artificial Intelligence
Classifier: Topic :: Database
Requires-Python: >=3.10
License-File: LICENSE
Requires-Dist: pandas>=2.0.0
Requires-Dist: numpy>=1.24.0
Requires-Dist: pydantic>=2.0.0
Requires-Dist: click>=8.1.0
Requires-Dist: pyyaml>=6.0
Requires-Dist: rich>=13.0.0
Requires-Dist: groq>=0.4.0
Requires-Dist: fastapi>=0.109.0
Requires-Dist: uvicorn>=0.27.0
Requires-Dist: python-multipart>=0.0.6
Requires-Dist: simpleeval>=0.9.0
Requires-Dist: scipy>=1.10.0
Provides-Extra: dev
Requires-Dist: pytest>=7.4.0; extra == "dev"
Requires-Dist: pytest-benchmark>=4.0.0; extra == "dev"
Requires-Dist: black>=23.0.0; extra == "dev"
Requires-Dist: ruff>=0.1.0; extra == "dev"
Requires-Dist: mypy>=1.5.0; extra == "dev"
Dynamic: license-file
